odoo10_addon_res_country_state_translations_canada-10.0.1.0.0.99.dev3-py3.8-nspkg.pth
odoo/addons/res_country_state_translations_canada/README.rst
odoo/addons/res_country_state_translations_canada/__init__.py
odoo/addons/res_country_state_translations_canada/__manifest__.py
odoo/addons/res_country_state_translations_canada/i18n/fr.po
odoo/addons/res_country_state_translations_canada/i18n/res_country_state_translations_canada.pot
odoo/addons/res_country_state_translations_canada/i18n_extra/fr.po
odoo/addons/res_country_state_translations_canada/readme/CONTRIBUTORS.rst
odoo/addons/res_country_state_translations_canada/readme/DESCRIPTION.rst
odoo/addons/res_country_state_translations_canada/static/description/icon.png
odoo/addons/res_country_state_translations_canada/static/description/index.html
odoo10_addon_res_country_state_translations_canada-10.0.1.0.0.99.dev3.dist-info/METADATA
odoo10_addon_res_country_state_translations_canada-10.0.1.0.0.99.dev3.dist-info/WHEEL
odoo10_addon_res_country_state_translations_canada-10.0.1.0.0.99.dev3.dist-info/namespace_packages.txt
odoo10_addon_res_country_state_translations_canada-10.0.1.0.0.99.dev3.dist-info/top_level.txt
odoo10_addon_res_country_state_translations_canada-10.0.1.0.0.99.dev3.dist-info/RECORD
